<annotation>
	<folder></folder>
	<filename>2118_png_jpg.rf.e65c21706ea14c794f6bc8640e4487c7.jpg</filename>
	<path>2118_png_jpg.rf.e65c21706ea14c794f6bc8640e4487c7.jpg</path>
	<source>
		<database>roboflow.com</database>
	</source>
	<size>
		<width>640</width>
		<height>640</height>
		<depth>3</depth>
	</size>
	<segmented>0</segmented>
	<object>
		<name>Hikkake Pattern</name>
		<pose>Unspecified</pose>
		<truncated>0</truncated>
		<difficult>0</difficult>
		<occluded>0</occluded>
		<bndbox>
			<xmin>165</xmin>
			<xmax>492</xmax>
			<ymin>99</ymin>
			<ymax>549</ymax>
		</bndbox>
	</object>
</annotation>
