<annotation>
	<folder></folder>
	<filename>839_png_jpg.rf.091c2fa84cde375fffe62aea05a29974.jpg</filename>
	<path>839_png_jpg.rf.091c2fa84cde375fffe62aea05a29974.jpg</path>
	<source>
		<database>roboflow.com</database>
	</source>
	<size>
		<width>640</width>
		<height>640</height>
		<depth>3</depth>
	</size>
	<segmented>0</segmented>
	<object>
		<name>Three Inside Up-Down</name>
		<pose>Unspecified</pose>
		<truncated>0</truncated>
		<difficult>0</difficult>
		<occluded>0</occluded>
		<bndbox>
			<xmin>295</xmin>
			<xmax>492</xmax>
			<ymin>99</ymin>
			<ymax>519</ymax>
		</bndbox>
	</object>
</annotation>
